ohk/__init__.py
ohk/ohk.py
ohk-0.0.1.dist-info/LICENSE
ohk-0.0.1.dist-info/METADATA
ohk-0.0.1.dist-info/WHEEL
ohk-0.0.1.dist-info/entry_points.txt
ohk-0.0.1.dist-info/top_level.txt
ohk-0.0.1.dist-info/RECORD
