Metadata-Version: 2.1
Name: ohk
Version: 0.0.1
Summary: An interactive alternative to grep and awk
Home-page: https://github.com/kbairak/ohk
Author: Konstantinos Bairaktaris
Author-email: ikijob@gmail.com
License: UNKNOWN
Platform: UNKNOWN
Classifier: Programming Language :: Python :: 3
Classifier: License :: OSI Approved :: GNU General Public License v3 (GPLv3)
Classifier: Operating System :: OS Independent
Requires-Python: >=3.7
License-File: LICENSE
Requires-Dist: urwid (==2.1.2)
